fload/__init__.py
fload/base.py
fload/cmd.py
fload/execute.py
fload/log.py
fload/cmds/__init__.py
fload/cmds/fload.py
fload/cmds/floadctl.py
fload/stream/__init__.py
fload/stream/pipeline/__init__.py
fload/stream/pipeline/filter.py
fload/stream/pipeline/last_field_to_file.py
fload/stream/pipeline/to_csv.py
fload/stream/source/__init__.py
fload/stream/source/csv.py
fload/stream/source/imap_scan.py
fload/stream/source/range.py
tests/__init__.py
tests/test_execute.py
tests/stream/__init__.py
tests/stream/source/__init__.py
tests/stream/source/test_csv.py
fload-0.0.6.dist-info/LICENSE
fload-0.0.6.dist-info/METADATA
fload-0.0.6.dist-info/WHEEL
fload-0.0.6.dist-info/entry_points.txt
fload-0.0.6.dist-info/top_level.txt
fload-0.0.6.dist-info/RECORD
