Metadata-Version: 2.1
Name: fload
Version: 0.0.6
Summary: fload is a data processing toolkit.
Home-page: http://github.com/kevenli/fload
Author: Keven Li
Author-email: pbleester@gmail.com
License: UNKNOWN
Platform: UNKNOWN
Requires-Dist: fasteners
Requires-Dist: pyaml
Requires-Dist: python-dateutil
Requires-Dist: six
